uplix/__about__.py
uplix/__init__.py
uplix/__main__.py
uplix-0.0.1.dist-info/METADATA
uplix-0.0.1.dist-info/WHEEL
uplix-0.0.1.dist-info/licenses/LICENSE.txt
uplix-0.0.1.dist-info/RECORD
