Metadata-Version: 2.1
Name: uplix
Version: 0.0.1
Project-URL: Documentation, https://github.com/ali-s-h/uplix#readme
Project-URL: Issues, https://github.com/ali-s-h/uplix/issues
Project-URL: Source, https://github.com/ali-s-h/uplix
Author-email: Ali <safarzadehali89@gmail.com>
License-Expression: MIT
License-File: LICENSE.txt
Classifier: Development Status :: 4 - Beta
Classifier: Programming Language :: Python
Classifier: Programming Language :: Python :: 3.7
Classifier: Programming Language :: Python :: 3.8
Classifier: Programming Language :: Python :: 3.9
Classifier: Programming Language :: Python :: 3.10
Classifier: Programming Language :: Python :: 3.11
Classifier: Programming Language :: Python :: Implementation :: CPython
Classifier: Programming Language :: Python :: Implementation :: PyPy
Requires-Python: >=3.7
